README.md
setup.py
active_campaign_python.egg-info/PKG-INFO
active_campaign_python.egg-info/SOURCES.txt
active_campaign_python.egg-info/dependency_links.txt
active_campaign_python.egg-info/not-zip-safe
active_campaign_python.egg-info/requires.txt
active_campaign_python.egg-info/top_level.txt
activecampaign/Account.py
activecampaign/ActiveCampaign.py
activecampaign/Campaign.py
activecampaign/Connector.py
activecampaign/Contact.py
activecampaign/Design.py
activecampaign/Form.py
activecampaign/Group.py
activecampaign/List.py
activecampaign/Message.py
activecampaign/Organization.py
activecampaign/User.py
activecampaign/__init__.py