Metadata-Version: 1.1
Name: active-campaign-python
Version: 0.9.2
Summary: Python ActiveCampaign API client
Home-page: https://github.com/tahoe/active-campaign-python
Author: Dennis Durling
Author-email: djdtahoe@gmail.com
License: MIT
Keywords: activecampaign
Platform: UNKNOWN
Classifier: Intended Audience :: Developers
Classifier: License :: OSI Approved :: BSD License
Classifier: Natural Language :: English
Classifier: Programming Language :: Python :: 2
Classifier: Programming Language :: Python :: 2.7
Classifier: Programming Language :: Python :: 3
Classifier: Programming Language :: Python :: 3.3
Classifier: Programming Language :: Python :: 3.4
Classifier: Programming Language :: Python :: 3.5
